[
  {
   "default": {
    "size_type": "auto_custom_max",
    "src": "https://5747173.fs1.hubspotusercontent-na1.net/hubfs/5747173/solutions-Hero%20image.png",
    "alt": "solutions-Hero image",
    "loading": "lazy",
    "width": 2118,
    "height": 1006,
    "max_width": 2000,
    "max_height": 949.9527856468367
   },
   "display_width": null,
   "id": "2a86805c-fca5-61f4-9d99-74bc65f447f9",
   "label": "Floating Graphic",
   "locked": false,
   "name": "floating_graphic",
   "required": false,
   "resizable": true,
   "responsive": true,
   "show_loading": false,
   "type": "image"
  },
  {
   "choices": [
    [
     "left",
     "Left"
    ],
    [
     "center",
     "Center"
    ],
    [
     "right",
     "Right"
    ]
   ],
   "default": "left",
   "display": "radio",
   "display_width": null,
   "id": "39b52964-f9be-7729-f5ea-be7c217b7515",
   "label": "Texture Position",
   "locked": false,
   "multiple": false,
   "name": "texture_position",
   "preset": null,
   "reordering_enabled": true,
   "required": false,
   "type": "choice"
  },
  {
   "default": 0,
   "display": "text",
   "display_width": null,
   "id": "da5fc715-2618-1f73-a902-19d5a8529e06",
   "label": "X axis",
   "locked": false,
   "max": 1000,
   "min": -1000,
   "name": "x_axis",
   "required": false,
   "step": 1,
   "type": "number"
  },
  {
   "default": -50,
   "display": "text",
   "display_width": null,
   "id": "d79bb44c-1ce5-ad8f-23e6-aac2fea51e07",
   "label": "Y Axis",
   "locked": false,
   "max": 1000,
   "min": -1000,
   "name": "y_axis",
   "required": false,
   "step": 1,
   "type": "number"
  }
 ]